{
  "appPageId" : "02d4ed5b-7ad5-4b38-bcd0-dac201935d75",
  "componentName" : "siteforce:sldsOneColLayout",
  "dataProviders" : [ ],
  "id" : "d6186655-7870-43bf-a1ed-784954aa974f",
  "label" : "Case List",
  "regions" : [ {
    "id" : "112ca84e-4b3c-42ea-8cc4-ce6f45e8a82a",
    "regionName" : "header",
    "type" : "region"
  }, {
    "components" : [ {
      "componentAttributes" : {
        "enableInlineEdit" : true,
        "filterName" : "{!filterId}",
        "layout" : "FULL",
        "pageSize" : 25,
        "scope" : "{!objectName}",
        "showActionBar" : true,
        "showChartsPanel" : true,
        "showDisplay" : "showall",
        "showFilterPanel" : true,
        "showImageIcon" : true,
        "showManualRefreshButton" : true,
        "showObjectName" : true,
        "showPinnedList" : true,
        "showSearchBar" : true
      },
      "componentName" : "forceCommunity:objectHome",
      "id" : "8cbc70ef-dd51-4446-96f2-aed17b98e78b",
      "renderPriority" : "NEUTRAL",
      "renditionMap" : { },
      "type" : "component"
    } ],
    "id" : "6f13822c-5cd9-4800-938d-ec8b2ff17ed9",
    "regionName" : "content",
    "type" : "region"
  }, {
    "id" : "09b5f24e-c145-49a0-82a3-0f2adfe64dba",
    "regionName" : "footer",
    "type" : "region"
  } ],
  "themeLayoutType" : "Inner",
  "type" : "view",
  "viewType" : "list-500"
}